nonebot_plugin_railwaytools/__init__.py
nonebot_plugin_railwaytools/api.py
nonebot_plugin_railwaytools/emu_function.py
nonebot_plugin_railwaytools/picture_function.py
nonebot_plugin_railwaytools/route_info.py
nonebot_plugin_railwaytools/station_info.py
nonebot_plugin_railwaytools/station_screen.py
nonebot_plugin_railwaytools/train_info.py
nonebot_plugin_railwaytools/utils.py
nonebot_plugin_railwaytools-2.2.0.dist-info/licenses/LICENSE
nonebot_plugin_railwaytools-2.2.0.dist-info/METADATA
nonebot_plugin_railwaytools-2.2.0.dist-info/WHEEL
nonebot_plugin_railwaytools-2.2.0.dist-info/top_level.txt
nonebot_plugin_railwaytools-2.2.0.dist-info/RECORD
