Metadata-Version: 2.4
Name: nonebot-plugin-railwaytools
Version: 2.2.0
Summary: 这是一个火车迷也许觉得很好用的铁路机器人工具箱
Author-email: leaf2006 <leafdeveloper@qq.com>
License-Expression: MIT
Project-URL: homepage, https://github.com/leaf2006/nonebot-plugin-railwaytools
Requires-Python: <4.0,>=3.9
License-File: LICENSE
Requires-Dist: nonebot2>=2.4.4
Requires-Dist: nonebot-adapter-onebot>=2.4.6
Requires-Dist: httpx>=0.22.0
Provides-Extra: dev
Requires-Dist: pyright[nodejs]; extra == "dev"
Requires-Dist: ruff; extra == "dev"
Dynamic: license-file
